UltraCrawler/__init__.py
UltraCrawler/test.py
UltraCrawler-0.0.2.dist-info/LICENSE
UltraCrawler-0.0.2.dist-info/METADATA
UltraCrawler-0.0.2.dist-info/WHEEL
UltraCrawler-0.0.2.dist-info/top_level.txt
UltraCrawler-0.0.2.dist-info/RECORD
