Metadata-Version: 2.1
Name: UltraCrawler
Version: 0.0.2
Summary: Ultra Crawler
Home-page: http://www.appx.xyz
Author: Appx
Author-email: appx@outlook.com
License: UNKNOWN
Platform: UNKNOWN
Classifier: Programming Language :: Python :: 3
Classifier: License :: OSI Approved :: MIT License
Classifier: Operating System :: OS Independent
